ssh_metro_client-0.1.2.dist-info/DESCRIPTION.rst
ssh_metro_client-0.1.2.dist-info/METADATA
ssh_metro_client-0.1.2.dist-info/RECORD
ssh_metro_client-0.1.2.dist-info/WHEEL
ssh_metro_client-0.1.2.dist-info/entry_points.txt
ssh_metro_client-0.1.2.dist-info/metadata.json
ssh_metro_client-0.1.2.dist-info/top_level.txt
sshmetroclient/__init__.py
sshmetroclient/main.py
