Metadata-Version: 2.0
Name: ssh-metro-client
Version: 0.1.2
Summary: An SSH tunnel client for SSH metro server
Home-page: https://github.com/thilux/ssh_metro_client
Author: thilux (Thiago Santana)
Author-email: thilux.systems@gmail.com
License: Apache 2
Keywords: python pexpect ssh requests tunnel ssh-tunnel argparse
Platform: UNKNOWN
Classifier: Development Status :: 3 - Alpha
Classifier: Intended Audience :: Developers
Classifier: Intended Audience :: Information Technology
Classifier: Intended Audience :: System Administrators
Classifier: License :: OSI Approved :: Apache Software License
Classifier: Topic :: Software Development :: Build Tools
Classifier: Programming Language :: Python
Classifier: Programming Language :: Python :: 2
Classifier: Programming Language :: Python :: 2.6
Classifier: Programming Language :: Python :: 2.7
Classifier: Programming Language :: Python :: 3
Classifier: Programming Language :: Python :: 3.4
Classifier: Programming Language :: Python :: 3.5
Classifier: Programming Language :: Python :: 3.6
Classifier: Programming Language :: Python :: Implementation :: CPython
Classifier: Programming Language :: Python :: Implementation :: PyPy
Requires-Python: >=2.6, !=3.0.*, !=3.1.*, !=3.2.*, !=3.3.*
Provides-Extra: testing
Requires-Dist: argparse
Requires-Dist: requests
Requires-Dist: pexpect
Provides-Extra: testing
Requires-Dist: argparse; extra == 'testing'
Requires-Dist: requests; extra == 'testing'
Requires-Dist: pexpect; extra == 'testing'
